deep_knowledge/__init__.py
deep_knowledge/generic_llm_provider.py
deep_knowledge/utils.py
deep_knowledge/summary/__init__.py
deep_knowledge/summary/prompts.py
deep_knowledge/summary/summary.py
deep_knowledge/summary/utils.py
deep_knowledge-0.1.10.dist-info/licenses/LICENSE
deep_knowledge-0.1.10.dist-info/METADATA
deep_knowledge-0.1.10.dist-info/WHEEL
deep_knowledge-0.1.10.dist-info/top_level.txt
deep_knowledge-0.1.10.dist-info/RECORD
