Metadata-Version: 2.4
Name: deep-knowledge
Version: 0.1.10
Summary: Deep Knowledge introduces a powerful multi-agent system for creating deep, comprehensive summaries of complex content.
Requires-Python: >=3.11
License-File: LICENSE
Requires-Dist: langchain-community>=0.3.20
Requires-Dist: langchain-core>=0.3.47
Requires-Dist: langchain-google-genai>=2.1.1
Requires-Dist: langchain-openai>=0.3.9
Requires-Dist: langchain-pymupdf4llm>=0.2.0
Requires-Dist: litellm>=1.63.14
Requires-Dist: loguru>=0.7.3
Requires-Dist: pypandoc>=1.15
Requires-Dist: python-decouple>=3.8
Requires-Dist: python-dotenv>=1.0.1
Requires-Dist: streamlit>=1.43.2
Requires-Dist: unstructured>=0.17.2
Dynamic: license-file
